bot/__init__.py
bot/bot.py
bot/eliza.py
bot/emulador.py
bot/telegram_api.py
bot/util.py
domoticaro/__init__.py
domoticaro/hardware/__init__.py
domoticaro/hardware/analogico.py
domoticaro/hardware/arduino.py
domoticaro/hardware/base.py
domoticaro/hardware/html_parser.py
domoticaro/hardware/html_weemos.py
domoticaro/hardware/humedad.py
domoticaro/hardware/icaro.py
domoticaro/hardware/lcd.py
domoticaro/hardware/relay.py
domoticaro/hardware/serie.py
domoticaro/hardware/serie_arduino.py
domoticaro/hardware/temperatura.py
domoticaro/hardware/weemos.py
voz/__init__.py
voz/espeak.py
DOMOTICARO-0.1.dist-info/AUTHORS
DOMOTICARO-0.1.dist-info/COPYING
DOMOTICARO-0.1.dist-info/METADATA
DOMOTICARO-0.1.dist-info/WHEEL
DOMOTICARO-0.1.dist-info/top_level.txt
DOMOTICARO-0.1.dist-info/RECORD
